chainalysis_sanction_verifier/__init__.py
chainalysis_sanction_verifier/client.py
chainalysis_sanction_verifier-0.1.2.dist-info/METADATA
chainalysis_sanction_verifier-0.1.2.dist-info/WHEEL
chainalysis_sanction_verifier-0.1.2.dist-info/RECORD
