Metadata-Version: 2.1
Name: chainalysis-sanction-verifier
Version: 0.1.2
Summary: 
Author: Matt Johnstone
Author-email: johnstone.mattjames@gmail.com
Requires-Python: >=3.11,<4.0
Classifier: Programming Language :: Python :: 3
Classifier: Programming Language :: Python :: 3.11
Classifier: Programming Language :: Python :: 3.12
Requires-Dist: httpx (>=0.23.0)
